odoo/addons/repair_comment_template/README.rst
odoo/addons/repair_comment_template/__init__.py
odoo/addons/repair_comment_template/__manifest__.py
odoo/addons/repair_comment_template/i18n/es.po
odoo/addons/repair_comment_template/i18n/it.po
odoo/addons/repair_comment_template/i18n/repair_comment_template.pot
odoo/addons/repair_comment_template/models/__init__.py
odoo/addons/repair_comment_template/models/repair_order.py
odoo/addons/repair_comment_template/readme/CONTRIBUTORS.rst
odoo/addons/repair_comment_template/readme/DESCRIPTION.rst
odoo/addons/repair_comment_template/readme/INSTALL.rst
odoo/addons/repair_comment_template/security/ir.model.access.csv
odoo/addons/repair_comment_template/static/description/icon.png
odoo/addons/repair_comment_template/static/description/index.html
odoo/addons/repair_comment_template/tests/__init__.py
odoo/addons/repair_comment_template/tests/test_repair_order_comments.py
odoo/addons/repair_comment_template/views/base_comment_template_views.xml
odoo/addons/repair_comment_template/views/repair_order_views.xml
odoo/addons/repair_comment_template/views/report_repairorder.xml
odoo_addon_repair_comment_template-16.0.1.0.0.4.dist-info/METADATA
odoo_addon_repair_comment_template-16.0.1.0.0.4.dist-info/WHEEL
odoo_addon_repair_comment_template-16.0.1.0.0.4.dist-info/top_level.txt
odoo_addon_repair_comment_template-16.0.1.0.0.4.dist-info/RECORD
